{
  "generator-jhipster": {
    "applicationType": "gateway",
    "gitHubOrganization": "yehdih2001",
    "baseName": "jhipsterSampleApplication",
    "packageName": "io.github.jhipster.application",
    "serverPort": 8080,
    "serviceDiscoveryType": "eureka",
    "authenticationType": "jwt",
    "uaaBaseName": "../uaa",
    "cacheProvider": "hazelcast",
    "enableHibernateCache": true,
    "websocket": false,
    "databaseType": "sql",
    "devDatabaseType": "h2Disk",
    "prodDatabaseType": "mariadb",
    "searchEngine": "elasticsearch",
    "enableSwaggerCodegen": "true",
    "messageBroker": "kafka",
    "buildTool": "maven",
    "enableSocialSignIn": false,
    "useSass": true,
    "clientPackageManager": "yarn",
    "testFrameworks": [
      "cucumber"
    ],
    "enableTranslation": true,
    "nativeLanguage": "en",
    "languages": [
      "ar-ly",
      "fr",
      "en"
    ],
    "clientFramework": "angularX",
    "jhipsterVersion": "4.14.4",
    "packageFolder": "io/github/jhipster/application",
    "jwtSecretKey": "1b245e373e8820c1d6b959339425d4bba3e0b7b4",
    "jhiPrefix": "jhi"
  }
}